mlinvitrotox/__init__.py
mlinvitrotox/__main__.py
mlinvitrotox/constants.py
mlinvitrotox/app/Results.py
mlinvitrotox/app/helper.py
mlinvitrotox/app/pages/01_ML_validation.py
mlinvitrotox/app/pages/01_ML_validation_summary.py
mlinvitrotox/apply/extractsiriusdata.py
mlinvitrotox/apply/loadfromhrms.py
mlinvitrotox/apply/loadfromstructure.py
mlinvitrotox/apply/runmodels.py
mlinvitrotox/config/config.yaml
mlinvitrotox/config/config_classification.yaml
mlinvitrotox/data/csi_fingerid.tsv
mlinvitrotox/train/evaluatemodels.py
mlinvitrotox/train/processinputdata.py
mlinvitrotox/train/providemodels.py
mlinvitrotox/train/trainmodels.py
mlinvitrotox/utils/extract_hrms_massbank_data.py
mlinvitrotox/utils/get_predicted_fps.py
mlinvitrotox/utils/get_true_fps.py
mlinvitrotox/utils/model.py
mlinvitrotox/utils/predict.py
mlinvitrotox/utils/training.py
mlinvitrotox/utils/validate_massbank.py
mlinvitrotox-0.3.5.dist-info/METADATA
mlinvitrotox-0.3.5.dist-info/WHEEL
mlinvitrotox-0.3.5.dist-info/entry_points.txt
mlinvitrotox-0.3.5.dist-info/licenses/LICENSE
mlinvitrotox-0.3.5.dist-info/RECORD
