Metadata-Version: 2.3
Name: MLinvitroTox
Version: 0.3.5
Summary: MLinvitroTox performs high-throughput hazard-based prioritization of high-resolution mass spectrometry data.
Author-email: Katarzyna Arturi <kasia.arturi@eawag.ch>, Lilian Gasser <lilian.gasser@sdsc.ethz.ch>, Matthias Meyer <matthias.meyer@sdsc.ethz.ch>, Eliza Harris <eliza.harris@sdsc.ethz.ch>
License-File: LICENSE
Requires-Python: >=3.8
Requires-Dist: cdk-pywrapper>=0.1.0
Requires-Dist: click>=8.1.7
Requires-Dist: filetype>=1.2.0
Requires-Dist: imbalanced-learn>=0.12.3
Requires-Dist: matplotlib>=3.9.0
Requires-Dist: numpy>=1.26.4
Requires-Dist: openbabel-wheel>=3.1.1.19
Requires-Dist: pandas>=2.2.2
Requires-Dist: plotly>=5.22.0
Requires-Dist: pyyaml>=6.0.1
Requires-Dist: rdkit>=2023.9.6
Requires-Dist: scikit-learn>=1.5.0
Requires-Dist: scipy>=1.13.1
Requires-Dist: seaborn>=0.13.2
Requires-Dist: streamlit>=1.35.0
Requires-Dist: tqdm>=4.66.4
Requires-Dist: xgboost>=2.0.3
